namecheap_cli/__init__.py
namecheap_cli/api.py
namecheap_cli/cli.py
namecheap_cli/config.py
namecheap_cli/utils.py
namecheap_cli-0.2.0.dist-info/licenses/LICENSE
namecheap_cli-0.2.0.dist-info/METADATA
namecheap_cli-0.2.0.dist-info/WHEEL
namecheap_cli-0.2.0.dist-info/entry_points.txt
namecheap_cli-0.2.0.dist-info/top_level.txt
namecheap_cli-0.2.0.dist-info/RECORD
