Metadata-Version: 2.4
Name: namecheap-cli
Version: 0.2.0
Summary: A command-line interface for managing Namecheap DNS records
Home-page: https://github.com/connorodea/namecheap-cli
Author: Connor O'Dea
Author-email: connor@example.com
Classifier: Programming Language :: Python :: 3
Classifier: License :: OSI Approved :: MIT License
Classifier: Operating System :: OS Independent
Requires-Python: >=3.6
License-File: LICENSE
Requires-Dist: requests>=2.25.0
Dynamic: author
Dynamic: author-email
Dynamic: classifier
Dynamic: description
Dynamic: description-content-type
Dynamic: home-page
Dynamic: license-file
Dynamic: requires-dist
Dynamic: requires-python
Dynamic: summary
